yuu/__init__.py
yuu/command.py
yuu/common.py
yuu/ext/__init__.py
yuu/ext/abematv.py
yuu/ext/aniplus.py
yuu/ext/bilibili.py
yuu/ext/gyao.py
yuu/ext/ponimu.py
yuu/yuutils/__init__.py
yuu/yuutils/helper.py
yuu/yuutils/jsAES.py
yuu-1.2.4.dist-info/LICENSE
yuu-1.2.4.dist-info/METADATA
yuu-1.2.4.dist-info/WHEEL
yuu-1.2.4.dist-info/entry_points.txt
yuu-1.2.4.dist-info/top_level.txt
yuu-1.2.4.dist-info/RECORD
