Metadata-Version: 2.1
Name: yuu
Version: 1.2.4
Summary: Yuu - A simple AbemaTV video downloader
Home-page: https://github.com/noaione/yuu
Author: noaione
Author-email: noaione0809@gmail.com
License: BSD-3-Clause
Keywords: ripping,downloader,parser
Platform: UNKNOWN
Classifier: Development Status :: 5 - Production/Stable
Classifier: License :: OSI Approved :: BSD License
Classifier: Programming Language :: Python :: 3
Classifier: Programming Language :: Python :: 3.5
Classifier: Programming Language :: Python :: 3.6
Classifier: Programming Language :: Python :: 3.7
Requires-Dist: requests[socks]
Requires-Dist: m3u8
Requires-Dist: tqdm
Requires-Dist: pycryptodome
Requires-Dist: click
